AUTHORS
CHANGELOG.txt
DESCRIPTION
LICENSE
MANIFEST.in
README.rst
setup.py
django_review.egg-info/PKG-INFO
django_review.egg-info/SOURCES.txt
django_review.egg-info/dependency_links.txt
django_review.egg-info/requires.txt
django_review.egg-info/top_level.txt
review/__init__.py
review/admin.py
review/compat.py
review/forms.py
review/models.py
review/urls.py
review/views.py
review/migrations/0001_initial.py
review/migrations/0002_auto_20180328_0620.py
review/migrations/__init__.py
review/south_migrations/0001_initial.py
review/south_migrations/0002_auto__add_field_review_average_rating.py
review/south_migrations/0003_auto__add_field_ratingcategory_identifier.py
review/south_migrations/0004_auto__del_ratingcategory__del_ratingcategorytranslation__del_field_rat.py
review/south_migrations/0005_auto__add_ratingcategory__add_ratingcategorytranslation__add_unique_ra.py
review/south_migrations/0006_auto__add_field_review_extra_content_type__add_field_review_extra_obje.py
review/south_migrations/0007_auto__add_ratingcategorychoicetranslation__add_unique_ratingcategorych.py
review/south_migrations/0008_auto__chg_field_ratingcategorychoice_value.py
review/south_migrations/0009_auto__add_field_ratingcategorytranslation_question.py
review/south_migrations/__init__.py
review/templates/review/review_confirm_delete.html
review/templates/review/review_detail.html
review/templates/review/review_form.html
review/templates/review/review_list.html
review/templates/review/partials/category_averages.html
review/templatetags/__init__.py
review/templatetags/review_tags.py
review/tests/__init__.py
review/tests/forms_tests.py
review/tests/models_tests.py
review/tests/review_tags_tests.py
review/tests/settings.py
review/tests/test_settings.py
review/tests/urls.py
review/tests/views_tests.py
review/tests/test_app/__init__.py
review/tests/test_app/forms.py
review/tests/test_app/models.py
review/tests/test_app/templates/400.html
review/tests/test_app/templates/500.html
review/tests/test_app/templates/base.html