Metadata-Version: 1.1
Name: django-review
Version: 1.10.0
Summary: A reusable Django app that lets users write reviews for any model
